[
  {
    "FirstName": "John",
    "LastName": "Doe",
    "CardDetails": {
      "CardNumber": "1234-5678-9812-3456",
      "ExpirationDate": "12/25",
      "Cvc": "123",
      "PinCode": "4321"
    },
    "TransactionHistory": [
      {
        "TransactionDate": "2024-02-16T21:19:38.9905595+04:00",
        "TransactionType": "Fill Amount",
        "AmountGel": 350.0,
        "AmountUsd": 0.0,
        "AmountEur": 35.00
      },
      {
        "TransactionDate": "2024-02-16T21:19:13.8250878+04:00",
        "TransactionType": "Change PIN",
        "AmountGel": 300.0,
        "AmountUsd": 0.0,
        "AmountEur": 35.00
      },
      {
        "TransactionDate": "2024-02-16T21:18:34.1416635+04:00",
        "TransactionType": "Check Balance",
        "AmountGel": 300.0,
        "AmountUsd": 0.0,
        "AmountEur": 35.00
      },
      {
        "TransactionDate": "2024-02-16T21:18:26.123036+04:00",
        "TransactionType": "Withdrawal",
        "AmountGel": 300.0,
        "AmountUsd": 0.0,
        "AmountEur": 35.00
      },
      {
        "TransactionDate": "2024-02-16T21:18:00.0756078+04:00",
        "TransactionType": "Currency Conversion to EUR",
        "AmountGel": 500.0,
        "AmountUsd": 0.0,
        "AmountEur": 35.00
      },
      {
        "TransactionDate": "2024-02-16T21:17:37.7130688+04:00",
        "TransactionType": "Fill Amount",
        "AmountGel": 600.0,
        "AmountUsd": 0.0,
        "AmountEur": 0.0
      },
      {
        "TransactionDate": "2024-01-03T14:15:30+04:00",
        "TransactionType": "BalanceInquiry",
        "AmountGel": 0.0,
        "AmountUsd": 0.0,
        "AmountEur": 0.0
      }
    ]
  },
  {
    "FirstName": "Jane",
    "LastName": "Smith",
    "CardDetails": {
      "CardNumber": "9876-5432-1234-5678",
      "ExpirationDate": "11/23",
      "Cvc": "456",
      "PinCode": "5678"
    },
    "TransactionHistory": [
      {
        "TransactionDate": "2024-01-03T14:15:30+04:00",
        "TransactionType": "BalanceInquiry",
        "AmountGel": 0.0,
        "AmountUsd": 0.0,
        "AmountEur": 0.0
      }
    ]
  }
]